[
  {
    "French": "Je vais acheter un nuevo sac de voyage pour mon prochain voyage.",
    "English": "I'm going to buy a new travel bag for my next trip."
  },
  {
    "French": "J'aime bien cette boutique de mode pour les achats en ligne.",
    "English": "I like this fashion online store for shopping."
  },
  {
    "French": "Cette publicité m'a fait découvrir une nouvelle marque de chaussures.",
    "English": "This ad introduced me to a new shoe brand."
  },
  {
    "French": "Je suis tombé sur un site de vente en gros pour acheter des produits à bas prix.",
    "English": "I stumbled upon a wholesale website to buy products at low prices."
  },
  {
    "French": "J'ai choisi ce magasin pour mon achat car il propose une garantie de qualité.",
    "English": "I chose this store for my purchase because it offers a quality guarantee."
  }
]
