[
  {
    "French": "Il y a un incendie dans le bâtiment !",
    "English": "There is a fire in the building!"
  },
  {
    "French": "Appelez les secours immédiatement !",
    "English": "Call for emergency assistance immediately!"
  },
  {
    "French": "Mon frère s'est blessé gravement.",
    "English": "My brother has been seriously injured."
  },
  {
    "French": "Je suis bloqué dans l'escalier avec une jambe cassée.",
    "English": "I am stuck in the stairwell with a broken leg."
  },
  {
    "French": "Il y a une bombe dans le sac de cet homme !",
    "English": "There is a bomb in that man's bag!"
  }
]
