   [
    {
      "French": "La France est une république démocratique.",
      "English": "France is a democratic republic."
    },
    {
      "French": "Le Président de la République française est élu pour une durée de cinq ans.",
      "English": "The President of the French Republic is elected for a five-year term."
    },
    {
      "French": "Le Parlement français est bicaméral et composé d'une assemblée nationale et d'un sénat.",
      "English": "The French Parliament is bicameral and composed of a National Assembly and a Senate."
    },
    {
      "French": "La Constitution française est adoptée en 1958 et modifiée plusieurs fois depuis.",
      "English": "The French Constitution was adopted in 1958 and has been modified several times since."
    },
    {
      "French": "Le système politique français est un mélange de démocratie et de centralisation.",
      "English": "The political system of France is a mix of democracy and centralization."
    }
   ]
