[
  {
    "French": "Je suis responsable de la gestion des ressources humaines dans notre entreprise.",
    "English": "I am responsible for human resource management in our company."
  },
  {
    "French": "Nous avons besoin d'un spécialiste en marketing numérique pour développer notre stratégie de promotion.",
    "English": "We need a digital marketing specialist to develop our promotional strategy."
  },
  {
    "French": "Je suis en train de préparer un rapport sur les performances de notre équipe de gestion de projet.",
    "English": "I am preparing a report on the performance of our project management team."
  },
  {
    "French": "Nous avons créé une nouvelle division pour gérer nos activités de vente à distance.",
    "English": "We have created a new department to manage our e-commerce activities."
  },
  {
    "French": "Je suis en train d'analyser les données de notre étude de marché pour identifier les tendances actuelles.",
    "English": "I am analyzing the data from our market study to identify current trends."
  }
]
